git_json_changes/__aimport__
git_json_changes/__init__.py
git_json_changes/cli.py
git_json_changes/constants.py
git_json_changes/core.py
git_json_changes/git_module.py
git_json_changes/github_adapter.py
git_json_changes/gitlab_adapter.py
git_json_changes/issue_module.py
git_json_changes/jira_adapter.py
git_json_changes/pr_module.py
git_json_changes/utils.py
git_json_changes-0.2.8.dist-info/METADATA
git_json_changes-0.2.8.dist-info/WHEEL
git_json_changes-0.2.8.dist-info/entry_points.txt
git_json_changes-0.2.8.dist-info/licenses/LICENSE
git_json_changes-0.2.8.dist-info/RECORD
