Metadata-Version: 2.4
Name: git-json-changes
Version: 0.2.8
Summary: Extract structured JSON of Git changes with PR and issue tracker integration
License: Proprietary
License-File: LICENSE
Requires-Python: >=3.10
Requires-Dist: click>=8.0
Requires-Dist: gitpython>=3.1
Requires-Dist: loguru>=0.7
Requires-Dist: requests>=2.28
